{
  "COP": {
    "multipleDevices": {
      "id": "43da9488-07a0-4c36-aa76-587bc62707ff6",
      "steps": [
        "DEVICE_GALLERY",
        "DEVICE_DETAILS",
        "REVIEW_BASKET"
      ],
      "description": "Generic COP flow for multiple devices in the cart"
    },
    "defaultScenario": {
      "id": "374323dd-d091-4164-993a-3dcce359bca3",
      "steps": [
        "DEVICE_GALLERY",
        "REVIEW_BASKET"
      ],
      "description": "Generic COP flow for one device in the cart"
    }
  }
}
